pm2mp/__init__.py
pm2mp/package-lock.json
pm2mp/package.json
pm2mp/pm2mp.py
pm2mp/pm2wrapper.js
pm2mp-0.0.97.data/data/pm2/package-lock.json
pm2mp-0.0.97.data/data/pm2/package.json
pm2mp-0.0.97.data/data/pm2/pm2wrapper.js
pm2mp-0.0.97.dist-info/METADATA
pm2mp-0.0.97.dist-info/WHEEL
pm2mp-0.0.97.dist-info/top_level.txt
pm2mp-0.0.97.dist-info/RECORD
